{
"meta":{"test_sets":[],"test_metrics":[],"learn_metrics":[{"best_value":"Min","name":"Logloss"}],"launch_mode":"Train","parameters":"","iteration_count":100,"learn_sets":["learn"],"name":"experiment"},
"iterations":[
{"learn":[0.6923106264],"iteration":0,"passed_time":0.1300632631,"remaining_time":12.87626305},
{"learn":[0.6914375572],"iteration":1,"passed_time":0.1310083439,"remaining_time":6.419408853},
{"learn":[0.6904289114],"iteration":2,"passed_time":0.1315697229,"remaining_time":4.254087708},
{"learn":[0.6895993791],"iteration":3,"passed_time":0.1322891864,"remaining_time":3.174940473},
{"learn":[0.6889771443],"iteration":4,"passed_time":0.1327315763,"remaining_time":2.52189995},
{"learn":[0.6876895819],"iteration":5,"passed_time":0.133186357,"remaining_time":2.08658626},
{"learn":[0.686496762],"iteration":6,"passed_time":0.1337897177,"remaining_time":1.777491963},
{"learn":[0.6853342853],"iteration":7,"passed_time":0.1342940012,"remaining_time":1.544381013},
{"learn":[0.6843359965],"iteration":8,"passed_time":0.1349329299,"remaining_time":1.364321846},
{"learn":[0.683671829],"iteration":9,"passed_time":0.1355101454,"remaining_time":1.219591308},
{"learn":[0.6824882357],"iteration":10,"passed_time":0.1361052107,"remaining_time":1.101214887},
{"learn":[0.6815475426],"iteration":11,"passed_time":0.1365833304,"remaining_time":1.00161109},
{"learn":[0.6806098086],"iteration":12,"passed_time":0.137126539,"remaining_time":0.917692992},
{"learn":[0.6794325798],"iteration":13,"passed_time":0.1377706364,"remaining_time":0.8463053378},
{"learn":[0.6789879515],"iteration":14,"passed_time":0.1383586199,"remaining_time":0.7840321794},
{"learn":[0.6783844928],"iteration":15,"passed_time":0.1388287563,"remaining_time":0.7288509704},
{"learn":[0.6774545246],"iteration":16,"passed_time":0.1392952065,"remaining_time":0.680088361},
{"learn":[0.6768250461],"iteration":17,"passed_time":0.1398135835,"remaining_time":0.6369285473},
{"learn":[0.67619717],"iteration":18,"passed_time":0.1404514305,"remaining_time":0.5987666246},
{"learn":[0.6752744069],"iteration":19,"passed_time":0.1410708666,"remaining_time":0.5642834662},
{"learn":[0.6744908711],"iteration":20,"passed_time":0.1415280312,"remaining_time":0.5324149747},
{"learn":[0.673563648],"iteration":21,"passed_time":0.1418226841,"remaining_time":0.50282588},
{"learn":[0.6727744357],"iteration":22,"passed_time":0.1423356321,"remaining_time":0.4765149422},
{"learn":[0.6720206858],"iteration":23,"passed_time":0.1428460959,"remaining_time":0.4523459704},
{"learn":[0.6712303071],"iteration":24,"passed_time":0.1431959311,"remaining_time":0.4295877932},
{"learn":[0.67008929],"iteration":25,"passed_time":0.1436214628,"remaining_time":0.4087687788},
{"learn":[0.6695086745],"iteration":26,"passed_time":0.1441202672,"remaining_time":0.3896585001},
{"learn":[0.6688626363],"iteration":27,"passed_time":0.1447354562,"remaining_time":0.3721768873},
{"learn":[0.6684381747],"iteration":28,"passed_time":0.1451855991,"remaining_time":0.3554543978},
{"learn":[0.6675041409],"iteration":29,"passed_time":0.1456370643,"remaining_time":0.3398198166},
{"learn":[0.6665533168],"iteration":30,"passed_time":0.1461418786,"remaining_time":0.3252835363},
{"learn":[0.6658186292],"iteration":31,"passed_time":0.1466243857,"remaining_time":0.3115768196},
{"learn":[0.6650560308],"iteration":32,"passed_time":0.1470433565,"remaining_time":0.2985425723},
{"learn":[0.6637651308],"iteration":33,"passed_time":0.1476258408,"remaining_time":0.2865678086},
{"learn":[0.6630005224],"iteration":34,"passed_time":0.1481188354,"remaining_time":0.2750778372},
{"learn":[0.6619047324],"iteration":35,"passed_time":0.1485235023,"remaining_time":0.2640417818},
{"learn":[0.6609687143],"iteration":36,"passed_time":0.1490425104,"remaining_time":0.2537750853},
{"learn":[0.6600505155],"iteration":37,"passed_time":0.1496184137,"remaining_time":0.2441142539},
{"learn":[0.6593019946],"iteration":38,"passed_time":0.1500870476,"remaining_time":0.2347515359},
{"learn":[0.6585268246],"iteration":39,"passed_time":0.1506993618,"remaining_time":0.2260490426},
{"learn":[0.6582575018],"iteration":40,"passed_time":0.1511125028,"remaining_time":0.2174545772},
{"learn":[0.6576925574],"iteration":41,"passed_time":0.1514763815,"remaining_time":0.2091816696},
{"learn":[0.6569763861],"iteration":42,"passed_time":0.1519822075,"remaining_time":0.2014647867},
{"learn":[0.6565445587],"iteration":43,"passed_time":0.152417155,"remaining_time":0.1939854701},
{"learn":[0.6559207737],"iteration":44,"passed_time":0.1529971452,"remaining_time":0.1869965108},
{"learn":[0.6554997034],"iteration":45,"passed_time":0.1534147136,"remaining_time":0.1800955334},
{"learn":[0.6545409709],"iteration":46,"passed_time":0.1540378159,"remaining_time":0.1737022179},
{"learn":[0.65396545],"iteration":47,"passed_time":0.1544775514,"remaining_time":0.1673506807},
{"learn":[0.6531999765],"iteration":48,"passed_time":0.1551190444,"remaining_time":0.161450434},
{"learn":[0.6524560543],"iteration":49,"passed_time":0.1557298661,"remaining_time":0.1557298661},
{"learn":[0.652056593],"iteration":50,"passed_time":0.156206323,"remaining_time":0.1500805849},
{"learn":[0.6514893671],"iteration":51,"passed_time":0.1567419289,"remaining_time":0.1446848575},
{"learn":[0.6502411854],"iteration":52,"passed_time":0.1573031677,"remaining_time":0.1394952619},
{"learn":[0.6493329696],"iteration":53,"passed_time":0.1577119114,"remaining_time":0.1343471838},
{"learn":[0.648260788],"iteration":54,"passed_time":0.1581561244,"remaining_time":0.1294004654},
{"learn":[0.6474630866],"iteration":55,"passed_time":0.1587034299,"remaining_time":0.124695552},
{"learn":[0.6464705989],"iteration":56,"passed_time":0.1591067445,"remaining_time":0.1200278949},
{"learn":[0.646046468],"iteration":57,"passed_time":0.1595920963,"remaining_time":0.1155666904},
{"learn":[0.6452950968],"iteration":58,"passed_time":0.1600996152,"remaining_time":0.1112556648},
{"learn":[0.6445679317],"iteration":59,"passed_time":0.1606486536,"remaining_time":0.1070991024},
{"learn":[0.6438195937],"iteration":60,"passed_time":0.1612298257,"remaining_time":0.1030813639},
{"learn":[0.6430740406],"iteration":61,"passed_time":0.1618690348,"remaining_time":0.09921005361},
{"learn":[0.6424941421],"iteration":62,"passed_time":0.1625421407,"remaining_time":0.09546125724},
{"learn":[0.6419617799],"iteration":63,"passed_time":0.1630351253,"remaining_time":0.09170725799},
{"learn":[0.6411376993],"iteration":64,"passed_time":0.1636067815,"remaining_time":0.08809595927},
{"learn":[0.6402450701],"iteration":65,"passed_time":0.1641093321,"remaining_time":0.08454117108},
{"learn":[0.6396449705],"iteration":66,"passed_time":0.1647277866,"remaining_time":0.08113458144},
{"learn":[0.6388633649],"iteration":67,"passed_time":0.1652838767,"remaining_time":0.07778064786},
{"learn":[0.6381240802],"iteration":68,"passed_time":0.1658117296,"remaining_time":0.0744951249},
{"learn":[0.6375601788],"iteration":69,"passed_time":0.1663245073,"remaining_time":0.07128193171},
{"learn":[0.6365325186],"iteration":70,"passed_time":0.1667172142,"remaining_time":0.06809576354},
{"learn":[0.6358244386],"iteration":71,"passed_time":0.1671139077,"remaining_time":0.06498874189},
{"learn":[0.6351120803],"iteration":72,"passed_time":0.1676498241,"remaining_time":0.0620074692},
{"learn":[0.6342661596],"iteration":73,"passed_time":0.1680544209,"remaining_time":0.05904614788},
{"learn":[0.6337887347],"iteration":74,"passed_time":0.1684673215,"remaining_time":0.05615577384},
{"learn":[0.6334969948],"iteration":75,"passed_time":0.1688258813,"remaining_time":0.05331343619},
{"learn":[0.6327931633],"iteration":76,"passed_time":0.1693711133,"remaining_time":0.0505913715},
{"learn":[0.6323184255],"iteration":77,"passed_time":0.1697223408,"remaining_time":0.0478704038},
{"learn":[0.6319454743],"iteration":78,"passed_time":0.1701739061,"remaining_time":0.04523610161},
{"learn":[0.6309446461],"iteration":79,"passed_time":0.1705799452,"remaining_time":0.04264498631},
{"learn":[0.6299514025],"iteration":80,"passed_time":0.171026983,"remaining_time":0.04011744045},
{"learn":[0.629259636],"iteration":81,"passed_time":0.1715236938,"remaining_time":0.03765154254},
{"learn":[0.6282150381],"iteration":82,"passed_time":0.1720922348,"remaining_time":0.03524780712},
{"learn":[0.6276221838],"iteration":83,"passed_time":0.1726409526,"remaining_time":0.03288399097},
{"learn":[0.6269369473],"iteration":84,"passed_time":0.1731296901,"remaining_time":0.03055229825},
{"learn":[0.6258991427],"iteration":85,"passed_time":0.1736758737,"remaining_time":0.02827281664},
{"learn":[0.6246252606],"iteration":86,"passed_time":0.1740308574,"remaining_time":0.02600461088},
{"learn":[0.623681186],"iteration":87,"passed_time":0.1745379256,"remaining_time":0.02380062622},
{"learn":[0.6231081386],"iteration":88,"passed_time":0.175072059,"remaining_time":0.02163811965},
{"learn":[0.6220373246],"iteration":89,"passed_time":0.175537758,"remaining_time":0.01950419533},
{"learn":[0.6212703851],"iteration":90,"passed_time":0.1760324053,"remaining_time":0.01740979833},
{"learn":[0.6205704593],"iteration":91,"passed_time":0.1766239448,"remaining_time":0.0153586039},
{"learn":[0.6194745484],"iteration":92,"passed_time":0.1770423947,"remaining_time":0.01332577165},
{"learn":[0.6186699917],"iteration":93,"passed_time":0.1775666316,"remaining_time":0.01133404031},
{"learn":[0.617721195],"iteration":94,"passed_time":0.1779848912,"remaining_time":0.009367625852},
{"learn":[0.6166640504],"iteration":95,"passed_time":0.1783997952,"remaining_time":0.0074333248},
{"learn":[0.6156549868],"iteration":96,"passed_time":0.1789244628,"remaining_time":0.005533746272},
{"learn":[0.6151369694],"iteration":97,"passed_time":0.1793314135,"remaining_time":0.003659824765},
{"learn":[0.6146190133],"iteration":98,"passed_time":0.1797272155,"remaining_time":0.001815426419},
{"learn":[0.613961637],"iteration":99,"passed_time":0.1802061166,"remaining_time":0}
]}